[{"authors":["gonza-zarza"],"categories":null,"content":"About me I hold a doctoral degree in High-Performance Computing and co-authored the book \u0026ldquo;Big Data Engineering, How to Deal with Data\u0026rdquo;.\nI currently serve as Technical Director in the Data \u0026amp; Analytics, and the Artificial Intelligence Studios at Globant, with a strong emphasis on data engineering and strategy. At Globant, I lead the Data Architecture practice at a global scale, leading a team of more than 180 highly skilled professionals located in USA, Europe, India and Latin America.\n In the academic field, I have lectured graduate and postgraduate courses at the Escola d\u0026rsquo;Enginyeria from the Universitat Aunònoma de Barcelona (UAB) for more than five years. Since 2016, I teach Data and Analytics in Masters degrees of the Business School at the Universidad Argentina de la Empresa (UADE).\nIn addition, I frequently speak at conferences and events about Big Data, High-Performance Computing and Artificial Intelligence.\n","date":-62135596800,"expirydate":-62135596800,"kind":"taxonomy","lang":"en","lastmod":-62135596800,"objectID":"cba6d450af2393a8fdc2ef1e6cedea7a","permalink":"https://www.gonzalozarza.me/authors/gonza-zarza/","publishdate":"0001-01-01T00:00:00Z","relpermalink":"/authors/gonza-zarza/","section":"authors","summary":"About me I hold a doctoral degree in High-Performance Computing and co-authored the book \u0026ldquo;Big Data Engineering, How to Deal with Data\u0026rdquo;.\nI currently serve as Technical Director in the Data \u0026amp; Analytics, and the Artificial Intelligence Studios at Globant, with a strong emphasis on data engineering and strategy. At Globant, I lead the Data Architecture practice at a global scale, leading a team of more than 180 highly skilled professionals located in USA, Europe, India and Latin America.","tags":null,"title":"Gonzalo Zarza","type":"authors"}]